catdir/__init__.py
catdir/constants.py
catdir/dump.py
catdir/main.py
catdir-0.1.2.dist-info/licenses/LICENSE
tests/__init__.py
tests/test_main.py
catdir-0.1.2.dist-info/METADATA
catdir-0.1.2.dist-info/WHEEL
catdir-0.1.2.dist-info/entry_points.txt
catdir-0.1.2.dist-info/top_level.txt
catdir-0.1.2.dist-info/RECORD
